fixer/__init__.py
fixer/config.py
fixer/handler.py
fixer_demo-0.1.0.dist-info/METADATA
fixer_demo-0.1.0.dist-info/WHEEL
fixer_demo-0.1.0.dist-info/top_level.txt
fixer_demo-0.1.0.dist-info/RECORD
