Metadata-Version: 2.1
Name: fixer-demo
Version: 0.1.0
Summary: Fixer Demo
Author: Amir
Author-email: amirb938@gmail.com
License: MIT
